font_fjallaone/__init__.py
font_fjallaone/files/FjallaOne-Regular.ttf
font_fjallaone-0.1.7.dist-info/METADATA
font_fjallaone-0.1.7.dist-info/WHEEL
font_fjallaone-0.1.7.dist-info/entry_points.txt
font_fjallaone-0.1.7.dist-info/RECORD
