Metadata-Version: 2.4
Name: font-fjallaone
Version: 0.1.7
Summary: Fjalla One from from Sorkin Type as distributed by Google Fonts
Author: RaBe IT-Reaktion
Author-email: it@rabe.ch
Requires-Python: >=3.11,<4.0
Classifier: Programming Language :: Python :: 3
Classifier: Programming Language :: Python :: 3.11
Classifier: Programming Language :: Python :: 3.12
Classifier: Programming Language :: Python :: 3.13
Classifier: Programming Language :: Python :: 3.14
